hf_downloader/__init__.py
hf_downloader/cli.py
hf_downloader/core_api.py
hf_downloader/experimenting.py
hf_downloader/utils.py
hf_model_downloader-0.0.1.dist-info/LICENSE
hf_model_downloader-0.0.1.dist-info/METADATA
hf_model_downloader-0.0.1.dist-info/WHEEL
hf_model_downloader-0.0.1.dist-info/entry_points.txt
hf_model_downloader-0.0.1.dist-info/top_level.txt
hf_model_downloader-0.0.1.dist-info/RECORD
