Metadata-Version: 2.1
Name: hf-model-downloader
Version: 0.0.1
Summary: HuggingFace model downloader
Home-page: https://github.com/muellerzr/hf-downloader
Author: Zach Mueller
Author-email: muellerzr@gmail.com
License: Apache
Keywords: deep learning
Classifier: Development Status :: 3 - Alpha
Classifier: Intended Audience :: Developers
Classifier: Intended Audience :: Education
Classifier: Intended Audience :: Science/Research
Classifier: License :: OSI Approved :: Apache Software License
Classifier: Operating System :: OS Independent
Classifier: Programming Language :: Python :: 3
Classifier: Programming Language :: Python :: 3.8
Classifier: Topic :: Scientific/Engineering :: Artificial Intelligence
Requires-Python: >=3.8.0
License-File: LICENSE
Requires-Dist: huggingface-hub (>=0.21.0)
Requires-Dist: hf-transfer (>=0.1.8)
